kvp/__init__.py
kvp/api.py
kvp/callers.py
kvp/cf.py
kvp/filter.py
kvp/picker.py
kvp/trigger.py
kvp/lib/__init__.py
kvp/lib/libkvp-maco.so
kvp-0.1.0.dist-info/licenses/LICENSE
kvp-0.1.0.dist-info/METADATA
kvp-0.1.0.dist-info/WHEEL
kvp-0.1.0.dist-info/top_level.txt
kvp-0.1.0.dist-info/RECORD
