Metadata-Version: 2.4
Name: kvp
Version: 0.1.0
Author-email: B-CSI <hlatorre@icm.csic.es>
License:                     GNU GENERAL PUBLIC LICENSE
Project-URL: Homepage, https://github.com/B-CSI/kvp
Project-URL: Bug Tracker, https://github.com/B-CSI/kvp/issues
Requires-Python: >=3.10
License-File: LICENSE
Requires-Dist: numpy>=1.23
Requires-Dist: fancy-ctypes>=0.2.1
Dynamic: license-file
